libmanconf/__init__.py
libmanconf/main.py
pnu_libmanconf-1.1.2.data/data/man/man3/libmanconf.3.gz
pnu_libmanconf-1.1.2.data/data/man/man5/man.conf.5.gz
pnu_libmanconf-1.1.2.dist-info/License
pnu_libmanconf-1.1.2.dist-info/METADATA
pnu_libmanconf-1.1.2.dist-info/WHEEL
pnu_libmanconf-1.1.2.dist-info/top_level.txt
pnu_libmanconf-1.1.2.dist-info/RECORD
